datanectar
