Metadata-Version: 2.1
Name: datanectar
Version: 0.1.4
Summary: Artifact tracking for luigi
Home-page: https://github.com/madconsulting/datanectar
Author: Wes Madrigal, Caleb Madrigal
Author-email: admin@madconsulting.ai
License: MIT
Keywords: data,luigi,ml
Platform: UNKNOWN
Classifier: License :: OSI Approved :: MIT License
Classifier: Programming Language :: Python :: 3
Classifier: Programming Language :: Python :: 3.5
Classifier: Programming Language :: Python :: 3.6
Classifier: Programming Language :: Python :: 3.7
Classifier: Programming Language :: Python :: 3.8
Classifier: Programming Language :: Python :: Implementation :: CPython
Classifier: Operating System :: POSIX :: Linux
Classifier: Operating System :: MacOS
